hoss/__init__.py
hoss/api.py
hoss/auth.py
hoss/cli.py
hoss/console.py
hoss/core.py
hoss/dataset.py
hoss/error.py
hoss/namespace.py
hoss/objectstore.py
hoss/ref.py
hoss/utilities.py
hoss/version.py
hoss/commands/__init__.py
hoss/commands/download.py
hoss/commands/upload.py
hoss/commands/version.py
hoss/tools/__init__.py
hoss/tools/common.py
hoss/tools/download.py
hoss/tools/upload.py
hoss_client-0.7.6.dist-info/LICENSE
hoss_client-0.7.6.dist-info/METADATA
hoss_client-0.7.6.dist-info/WHEEL
hoss_client-0.7.6.dist-info/entry_points.txt
hoss_client-0.7.6.dist-info/top_level.txt
hoss_client-0.7.6.dist-info/RECORD
