Metadata-Version: 2.1
Name: hoss-client
Version: 0.7.6
Summary: A client library and CLI for interacting with a Hoss server.
Home-page: https://github.com/WyssCenter/hoss-client
Author: Gigantum, Inc.
Author-email: support@gigantum.com
License: MIT
Keywords: data-science,science,gigantum,open-science,object-store,s3,minio
Classifier: Development Status :: 4 - Beta
Classifier: Programming Language :: Python :: 3.8
Classifier: Programming Language :: Python :: 3.7
Classifier: Programming Language :: Python :: 3.6
Requires-Python: >=3.6
License-File: LICENSE
Requires-Dist: requests
Requires-Dist: boto3
Requires-Dist: PyJWT
Requires-Dist: click
Requires-Dist: rich
Requires-Dist: humanize
Requires-Dist: packaging
Requires-Dist: nest-asyncio
